colcon_package_information/__init__.py
colcon_package_information/package_augmentation/__init__.py
colcon_package_information/package_augmentation/check_dependency_constraint.py
colcon_package_information/verb/__init__.py
colcon_package_information/verb/graph.py
colcon_package_information/verb/info.py
colcon_package_information/verb/list.py
colcon_package_information-0.3.2.dist-info/LICENSE
colcon_package_information-0.3.2.dist-info/METADATA
colcon_package_information-0.3.2.dist-info/WHEEL
colcon_package_information-0.3.2.dist-info/entry_points.txt
colcon_package_information-0.3.2.dist-info/top_level.txt
colcon_package_information-0.3.2.dist-info/zip-safe
colcon_package_information-0.3.2.dist-info/RECORD
